brute_force_cython_ext.cpython-311-x86_64-linux-gnu.so
imagededup/__init__.py
imagededup/evaluation/__init__.py
imagededup/evaluation/evaluation.py
imagededup/handlers/__init__.py
imagededup/handlers/metrics/__init__.py
imagededup/handlers/metrics/classification.py
imagededup/handlers/metrics/information_retrieval.py
imagededup/handlers/search/__init__.py
imagededup/handlers/search/bktree.py
imagededup/handlers/search/brute_force.py
imagededup/handlers/search/brute_force_cython.py
imagededup/handlers/search/brute_force_cython_ext.cpp
imagededup/handlers/search/brute_force_cython_ext.pyx
imagededup/handlers/search/retrieval.py
imagededup/handlers/search/builtin/README.md
imagededup/handlers/search/builtin/builtin.h
imagededup/methods/__init__.py
imagededup/methods/cnn.py
imagededup/methods/hashing.py
imagededup/utils/__init__.py
imagededup/utils/data_generator.py
imagededup/utils/general_utils.py
imagededup/utils/image_utils.py
imagededup/utils/logger.py
imagededup/utils/models.py
imagededup/utils/plotter.py
mkdocs/autogen.py
imagededup-0.3.3.post2.dist-info/METADATA
imagededup-0.3.3.post2.dist-info/WHEEL
imagededup-0.3.3.post2.dist-info/top_level.txt
imagededup-0.3.3.post2.dist-info/RECORD
imagededup-0.3.3.post2.dist-info/licenses/LICENSE
