Metadata-Version: 2.4
Name: imagededup
Version: 0.3.3.post2
Summary: Package for image deduplication
Author-email: Tanuj Jain <tanuj.jain.10@gmail.com>, Christopher Lennan <christopherlennan@gmail.com>, Zubin John <zrjohn@yahoo.com>, Dat Tran <datitran@gmail.com>
License-Expression: Apache-2.0
Project-URL: Documentation, https://idealo.github.io/imagededup/
Classifier: Development Status :: 5 - Production/Stable
Classifier: Intended Audience :: Developers
Classifier: Intended Audience :: Science/Research
Classifier: Operating System :: POSIX :: Linux
Classifier: Operating System :: MacOS :: MacOS X
Classifier: Operating System :: Microsoft :: Windows
Classifier: Programming Language :: Cython
Classifier: Programming Language :: Python :: 3
Classifier: Programming Language :: Python :: 3.9
Classifier: Programming Language :: Python :: 3.10
Classifier: Programming Language :: Python :: 3.11
Classifier: Programming Language :: Python :: 3.12
Classifier: Topic :: Software Development :: Libraries
Classifier: Topic :: Software Development :: Libraries :: Python Modules
Requires-Python: >=3.9
License-File: LICENSE
Requires-Dist: torch
Requires-Dist: torchvision
Requires-Dist: Pillow>=9.0
Requires-Dist: tqdm
Requires-Dist: scikit-learn
Requires-Dist: PyWavelets
Requires-Dist: matplotlib
Provides-Extra: tests
Requires-Dist: pytest; extra == "tests"
Requires-Dist: pytest-cov; extra == "tests"
Requires-Dist: pytest-mock; extra == "tests"
Requires-Dist: codecov; extra == "tests"
Provides-Extra: docs
Requires-Dist: mkdocs; extra == "docs"
Requires-Dist: mkdocs-material; extra == "docs"
Dynamic: license-file
